newrelic_lambda_cli/__init__.py
newrelic_lambda_cli/api.py
newrelic_lambda_cli/apm.py
newrelic_lambda_cli/cliutils.py
newrelic_lambda_cli/functions.py
newrelic_lambda_cli/integrations.py
newrelic_lambda_cli/layers.py
newrelic_lambda_cli/otel_ingestions.py
newrelic_lambda_cli/permissions.py
newrelic_lambda_cli/subscriptions.py
newrelic_lambda_cli/types.py
newrelic_lambda_cli/utils.py
newrelic_lambda_cli/cli/__init__.py
newrelic_lambda_cli/cli/apm.py
newrelic_lambda_cli/cli/decorators.py
newrelic_lambda_cli/cli/functions.py
newrelic_lambda_cli/cli/integrations.py
newrelic_lambda_cli/cli/layers.py
newrelic_lambda_cli/cli/otel_ingestions.py
newrelic_lambda_cli/cli/subscriptions.py
newrelic_lambda_cli/templates/import-template.yaml
newrelic_lambda_cli/templates/license-key-secret.yaml
newrelic_lambda_cli/templates/nr-lambda-integration-role.yaml
newrelic_lambda_cli-0.9.15.dist-info/licenses/LICENSE
newrelic_lambda_cli-0.9.15.dist-info/METADATA
newrelic_lambda_cli-0.9.15.dist-info/WHEEL
newrelic_lambda_cli-0.9.15.dist-info/entry_points.txt
newrelic_lambda_cli-0.9.15.dist-info/top_level.txt
newrelic_lambda_cli-0.9.15.dist-info/RECORD
