Metadata-Version: 2.4
Name: newrelic-lambda-cli
Version: 0.9.15
Summary: A CLI to install the New Relic AWS Lambda integration and layers.
Home-page: https://github.com/newrelic/newrelic-lambda-cli
Author: New Relic
Author-email: serverless-dev@newrelic.com
Requires-Python: >=3.3
License-File: LICENSE
Requires-Dist: boto3<5
Requires-Dist: click>=7.1.2
Requires-Dist: colorama
Requires-Dist: gql<3,>=2
Requires-Dist: requests<3
Requires-Dist: tabulate
Dynamic: author
Dynamic: author-email
Dynamic: description
Dynamic: description-content-type
Dynamic: home-page
Dynamic: license-file
Dynamic: requires-dist
Dynamic: requires-python
Dynamic: summary
